pytoon/__init__.py
pytoon/animator.py
pytoon/dataloader.py
pytoon/lipsync.py
pytoon/util.py
pytoon/assets/phonemes.json
pytoon/assets/pose_data.json
pytoon/assets/visemes.json
pytoon/assets/junk/json_files/data_templates.json
pytoon/assets/junk/json_files/og_coordinates_system.json
pytoon/assets/junk/scripts/img_database_schema_migration.py
pytoon/assets/poses/1.png
pytoon/assets/poses/10.png
pytoon/assets/poses/11.png
pytoon/assets/poses/12.png
pytoon/assets/poses/13.png
pytoon/assets/poses/14.png
pytoon/assets/poses/15.png
pytoon/assets/poses/16.png
pytoon/assets/poses/17.png
pytoon/assets/poses/18.png
pytoon/assets/poses/19.png
pytoon/assets/poses/2.png
pytoon/assets/poses/20.png
pytoon/assets/poses/21.png
pytoon/assets/poses/22.png
pytoon/assets/poses/23.png
pytoon/assets/poses/24.png
pytoon/assets/poses/25.png
pytoon/assets/poses/26.png
pytoon/assets/poses/27.png
pytoon/assets/poses/28.png
pytoon/assets/poses/29.png
pytoon/assets/poses/3.png
pytoon/assets/poses/30.png
pytoon/assets/poses/31.png
pytoon/assets/poses/32.png
pytoon/assets/poses/33.png
pytoon/assets/poses/34.png
pytoon/assets/poses/35.png
pytoon/assets/poses/36.png
pytoon/assets/poses/37.png
pytoon/assets/poses/38.png
pytoon/assets/poses/39.png
pytoon/assets/poses/4.png
pytoon/assets/poses/40.png
pytoon/assets/poses/41.png
pytoon/assets/poses/42.png
pytoon/assets/poses/43.png
pytoon/assets/poses/44.png
pytoon/assets/poses/45.png
pytoon/assets/poses/46.png
pytoon/assets/poses/47.png
pytoon/assets/poses/48.png
pytoon/assets/poses/49.png
pytoon/assets/poses/5.png
pytoon/assets/poses/50.png
pytoon/assets/poses/51.png
pytoon/assets/poses/52.png
pytoon/assets/poses/53.png
pytoon/assets/poses/54.png
pytoon/assets/poses/55.png
pytoon/assets/poses/56.png
pytoon/assets/poses/57.png
pytoon/assets/poses/58.png
pytoon/assets/poses/59.png
pytoon/assets/poses/6.png
pytoon/assets/poses/60.png
pytoon/assets/poses/61.png
pytoon/assets/poses/62.png
pytoon/assets/poses/63.png
pytoon/assets/poses/64.png
pytoon-1.5.0.dist-info/METADATA
pytoon-1.5.0.dist-info/WHEEL
pytoon-1.5.0.dist-info/top_level.txt
pytoon-1.5.0.dist-info/RECORD
