Metadata-Version: 2.1
Name: pytoon
Version: 1.5.0
Summary: A Python library for lip-syncing cartoons to voice recordings.
Home-page: https://github.com/lukerbs/apple
Author: Luke Kerbs
Keywords: animation,forced alignment,lip-sync,audio forced alignment,phoneme,generate subtitles
Classifier: Programming Language :: Python :: 3
Classifier: License :: OSI Approved :: MIT License
Classifier: Operating System :: OS Independent
Requires-Dist: forcealign >=1.1.9
Requires-Dist: moviepy
Requires-Dist: opencv-python
Requires-Dist: scipy
Requires-Dist: numpy
Requires-Dist: pillow
